<?xml version="1.0" encoding="utf-8"?>
<Root>
	<Data ID="1" GameName="经典捕鱼" GamePrefix="Fish" UpdateUrl="http://121.199.75.142:26011" IsOpen="false" GameSize="9.30M" ZipVersion="2.4.0" AnimationName="shuanglongbuyu" PictureName="shuanglongbuyu" IsShow="false" />
	<Data ID="2" GameName="鳄鱼大亨" GamePrefix="Crocodile" UpdateUrl="http://121.199.75.142:26011" IsOpen="false" GameSize="3.50M" ZipVersion="2.4.0" AnimationName="eyudaheng" PictureName="shuanglongbuyu" IsShow="false" />
	<Data ID="3" GameName="欢乐骰宝" GamePrefix="Dice" UpdateUrl="http://121.199.75.142:26011" IsOpen="false" GameSize="2.00M" ZipVersion="2.4.0" AnimationName="yaoyaole" PictureName="shuanglongbuyu" IsShow="false" />
	<Data ID="4" GameName="万人牛牛" GamePrefix="Cows" UpdateUrl="http://121.199.75.142:26011" IsOpen="false" GameSize="2.00M" ZipVersion="2.4.0" AnimationName="bairenniuniu" PictureName="shuanglongbuyu" IsShow="false" />
	<Data ID="5" GameName="百家乐" GamePrefix="Baccarat" UpdateUrl="http://121.199.75.142:26011" IsOpen="false" GameSize="2.00M" ZipVersion="2.4.0" AnimationName="jiangxiangheab" PictureName="shuanglongbuyu" IsShow="false" />
	<Data ID="6" GameName="五龙" GamePrefix="5Dragons" UpdateUrl="http://121.199.75.142:26011" IsOpen="false" GameSize="7.00M" ZipVersion="2.4.0" AnimationName="wulongzhengbaaabbc" PictureName="shuanglongbuyu" IsShow="false" />
	<Data ID="7" GameName="套牛" GamePrefix="CalfRoping" UpdateUrl="http://121.199.75.142:26011" IsOpen="false" GameSize="2.00M" ZipVersion="0.0.0" AnimationName="taoniujitai" PictureName="shuanglongbuyu" IsShow="false" />
	<Data ID="8" GameName="抓娃娃" GamePrefix="PrizeClaw" UpdateUrl="http://121.199.75.142:26011" IsOpen="false" GameSize="3.00M" ZipVersion="0.0.0" AnimationName="WAWAjitai" PictureName="shuanglongbuyu" IsShow="false" />
	<Data ID="9" GameName="鳄鱼公园" GamePrefix="FishPark" UpdateUrl="http://121.199.75.142:26011" IsOpen="false" GameSize="2.00M" ZipVersion="0.0.0" AnimationName="eyugongyuan" PictureName="shuanglongbuyu" IsShow="false" />
	<Data ID="10" GameName="黑红梅方" GamePrefix="ShcdCards" UpdateUrl="http://121.199.75.142:26011" IsOpen="false" GameSize="2.00M" ZipVersion="2.4.0" AnimationName="heihongmeifangab" PictureName="shuanglongbuyu" IsShow="false" />
	<Data ID="11" GameName="德州扑克" GamePrefix="TexasPoker" UpdateUrl="http://121.199.75.142:26011" IsOpen="false" GameSize="2.00M" ZipVersion="0.0.0" AnimationName="BAIJIALEjitai" PictureName="shuanglongbuyu" IsShow="false" />
	<Data ID="12" GameName="金鲨银鲨" GamePrefix="GoldShark" UpdateUrl="http://121.199.75.142:26011" IsOpen="false" GameSize="2.00M" ZipVersion="0.0.0" AnimationName="heihongmeifangab" PictureName="shuanglongbuyu" IsShow="false" />
	<Data ID="13" GameName="欢乐五张" GamePrefix="SuoHa" UpdateUrl="http://121.199.75.142:26011" IsOpen="false" GameSize="2.00M" ZipVersion="0.0.0" AnimationName="shuanglongbuyu" PictureName="shuanglongbuyu" IsShow="false" />
	<Data ID="14" GameName="欢乐至尊" GamePrefix="HappySupremacy" UpdateUrl="http://121.199.75.142:26011" IsOpen="false" GameSize="2.00M" ZipVersion="0.0.0" AnimationName="shuanglongbuyu" PictureName="shuanglongbuyu" IsShow="false" />
	<Data ID="15" GameName="斗地主" GamePrefix="Landlord" UpdateUrl="http://121.199.75.142:26011" IsOpen="true" GameSize="2.00M" ZipVersion="0.0.0" AnimationName="shuanglongbuyu" PictureName="shuanglongbuyu" IsShow="true" />
</Root>